unicodes_api
