Metadata-Version: 2.1
Name: unicodes
Version: 0.0.2
Summary: Quickly interact with unicode data via the cli, or api
Home-page: https://github.com/shollingsworth/unicodes
Author: Steven Hollingsworth
Author-email: hollingsworth.stevend@gmail.com
License: MIT
Project-URL: Changes, https://github.com/shollingsworth/unicodes/blob/main/CHANGELOG.md
Project-URL: Source Code, https://github.com/shollingsworth/unicodes
Project-URL: Issue Tracker, https://github.com/shollingsworth/unicodes/issues/
Project-URL: Twitter, https://twitter.com/_stevo
Project-URL: Documentation, https://shollingsworth.github.io/unicodes/index.html
Keywords: unicode,cli,terminal
Platform: UNKNOWN
Classifier: Development Status :: 5 - Production/Stable
Classifier: Environment :: Console
Classifier: Intended Audience :: Developers
Classifier: License :: OSI Approved :: MIT License
Classifier: Intended Audience :: End Users/Desktop
Classifier: Intended Audience :: Information Technology
Classifier: Operating System :: OS Independent
Classifier: Programming Language :: Python :: 3 :: Only
Classifier: Programming Language :: Python :: 3.6
Classifier: Programming Language :: Python :: 3.7
Classifier: Programming Language :: Python :: 3.8
Classifier: Programming Language :: Python :: 3.9
Classifier: Topic :: Documentation
Classifier: Topic :: Text Editors :: Documentation
Requires-Python: >=3.6
